argmagic.py
argmagic-1.0.1.dist-info/LICENSE.txt
argmagic-1.0.1.dist-info/METADATA
argmagic-1.0.1.dist-info/WHEEL
argmagic-1.0.1.dist-info/top_level.txt
argmagic-1.0.1.dist-info/RECORD
