Metadata-Version: 2.1
Name: argmagic
Version: 1.0.1
Summary: Parse environment variables and CLI arguments for a given function signature.
Home-page: https://github.com/xiamaz/argmagic
Author: Max Zhao
Author-email: alcasa.mz@gmail.com
License: UNKNOWN
Platform: UNKNOWN
Classifier: Programming Language :: Python :: 3
Classifier: License :: OSI Approved :: MIT License
Classifier: Operating System :: OS Independent
Requires-Python: >=3.6
